dockerclustermon/__init__.py
dockerclustermon-0.3.0.dist-info/METADATA
dockerclustermon-0.3.0.dist-info/WHEEL
dockerclustermon-0.3.0.dist-info/entry_points.txt
dockerclustermon-0.3.0.dist-info/licenses/LICENSE
dockerclustermon-0.3.0.dist-info/RECORD
