Metadata-Version: 2.4
Name: dockerclustermon
Version: 0.3.0
Summary: A CLI tool for a live view of your docker containers running on a remote server.
Project-URL: Homepage, https://github.com/mikeckennedy/dockerclustermon
Author-email: Michael Kennedy <michael@talkpython.fm>
License: MIT
License-File: LICENSE
Keywords: Docker,Docker Compose,Monitoring
Classifier: Development Status :: 4 - Beta
Classifier: License :: OSI Approved :: MIT License
Classifier: Programming Language :: Python
Classifier: Programming Language :: Python :: 3.10
Classifier: Programming Language :: Python :: 3.11
Classifier: Programming Language :: Python :: 3.12
Classifier: Programming Language :: Python :: 3.13
Classifier: Programming Language :: Python :: 3.14
Requires-Python: >=3.10
Requires-Dist: paramiko>=3.5.0
Requires-Dist: rich>=13.9.4
Requires-Dist: setproctitle>=1.3.7
Requires-Dist: typer>=0.13.1
